mindframe/__init__.py
mindframe/main.py
mindframe-0.1.0.dist-info/LICENSE
mindframe-0.1.0.dist-info/METADATA
mindframe-0.1.0.dist-info/WHEEL
mindframe-0.1.0.dist-info/top_level.txt
mindframe-0.1.0.dist-info/RECORD
