Metadata-Version: 2.1
Name: mindframe
Version: 0.1.0
Summary: A Python package for the Mindframe project
Author: Ben Whalley
Author-email: ben.whalley@plymouth.ac.uk
Classifier: Programming Language :: Python :: 3
Classifier: Operating System :: OS Independent
Requires-Python: >=3.6
License-File: LICENSE
